fusiondatatools/__init__.py
fusiondatatools/helpers.py
fusiondatatools/core/__init__.py
fusiondatatools/core/dataset.py
fusiondatatools/core/index.py
fusiondatatools/core/loader.py
fusiondatatools/core/parmap.py
fusiondatatools/core/transform.py
fusiondatatools/core/visualize.py
fusiondatatools/dataprep/dataprep.py
fusiondatatools/dataprep/dataprep2.py
fusiondatatools/dataprep/dataprep3.py
fusiondatatools/dataprep/dataprep4.py
fusiondatatools/dataprep/dataprep5.py
fusiondatatools/transform/__init__.py
fusiondatatools/transform/analysis.py
fusiondatatools/transform/binary.py
fusiondatatools/transform/co2cross.py
fusiondatatools/transform/hf.py
fusiondatatools/transform/ml.py
fusiondatatools-0.1.0.dist-info/licenses/LICENSE
fusiondatatools-0.1.0.dist-info/METADATA
fusiondatatools-0.1.0.dist-info/WHEEL
fusiondatatools-0.1.0.dist-info/top_level.txt
fusiondatatools-0.1.0.dist-info/RECORD
