Metadata-Version: 2.4
Name: fusiondatatools
Version: 0.1.0
Summary: Add your description here
Requires-Python: >=3.12
License-File: LICENSE
Requires-Dist: matplotlib>=3.10.3
Requires-Dist: numpy>=2.3.0
Requires-Dist: pandas>=2.3.0
Requires-Dist: torch>=2.7.1
Requires-Dist: tqdm>=4.67.1
Dynamic: license-file
